pirc522/__init__.py
pirc522/rfid.py
pirc522/util.py
pirc522/version.py
pi_rc522-2.3.0.dist-info/LICENSE.md
pi_rc522-2.3.0.dist-info/METADATA
pi_rc522-2.3.0.dist-info/WHEEL
pi_rc522-2.3.0.dist-info/top_level.txt
pi_rc522-2.3.0.dist-info/RECORD
